wagtail_maps/__init__.py
wagtail_maps/admin.py
wagtail_maps/apps.py
wagtail_maps/blocks.py
wagtail_maps/models.py
wagtail_maps/panels.py
wagtail_maps/urls.py
wagtail_maps/wagtail_hooks.py
wagtail_maps/api/__init__.py
wagtail_maps/api/serializers.py
wagtail_maps/api/views.py
wagtail_maps/locale/fr/LC_MESSAGES/django.mo
wagtail_maps/locale/fr/LC_MESSAGES/django.po
wagtail_maps/migrations/0001_initial.py
wagtail_maps/migrations/0002_remove_map_max_zoom_remove_map_min_zoom.py
wagtail_maps/migrations/__init__.py
wagtail_maps/static/wagtail_maps/css/admin-form.css
wagtail_maps/static/wagtail_maps/js/admin-form.js
wagtail_maps/static/wagtail_maps/js/admin-form.js.map
wagtail_maps/static/wagtail_maps/js/admin-form_controllers.js
wagtail_maps/static/wagtail_maps/js/admin-form_controllers.js.map
wagtail_maps/static/wagtail_maps/js/map-block.js
wagtail_maps/static/wagtail_maps/js/map-block.js.map
wagtail_maps/static/wagtail_maps/vendor/leaflet.css
wagtail_maps/static/wagtail_maps/vendor/images/layers-2x.png
wagtail_maps/static/wagtail_maps/vendor/images/layers.png
wagtail_maps/static/wagtail_maps/vendor/images/marker-icon-2x.png
wagtail_maps/static/wagtail_maps/vendor/images/marker-icon.png
wagtail_maps/static/wagtail_maps/vendor/images/marker-shadow.png
wagtail_maps/templates/wagtail_maps/map_block.html
wagtail_maps/templates/wagtail_maps/popup_content.html
wagtail_maps/templates/wagtail_maps/icons/map-pin.svg
wagtail_maps/templates/wagtail_maps/icons/map.svg
wagtail_maps/templates/wagtail_maps/panels/map_center_coordinates.html
wagtail_maps/templates/wagtail_maps/panels/point_coordinates.html
wagtail_maps-0.3.0.dist-info/LICENSE
wagtail_maps-0.3.0.dist-info/METADATA
wagtail_maps-0.3.0.dist-info/WHEEL
wagtail_maps-0.3.0.dist-info/top_level.txt
wagtail_maps-0.3.0.dist-info/RECORD
