Metadata-Version: 2.1
Name: wagtail-maps
Version: 0.3.0
Summary: Create and display maps with points in Wagtail
Author: Cliss XXI
Author-email: contact@cliss21.com
License: AGPLv3+
Project-URL: Bug Tracker, https://framagit.org/cliss21/wagtail-maps/-/issues
Project-URL: Source Code, https://framagit.org/cliss21/wagtail-maps
Keywords: wagtail,map,leaflet
Classifier: Development Status :: 3 - Alpha
Classifier: Environment :: Web Environment
Classifier: Framework :: Django
Classifier: Framework :: Wagtail
Classifier: Intended Audience :: Developers
Classifier: License :: OSI Approved :: GNU Affero General Public License v3
Classifier: Operating System :: OS Independent
Classifier: Programming Language :: Python :: 3
Classifier: Programming Language :: Python :: 3.8
Classifier: Programming Language :: Python :: 3.9
Classifier: Programming Language :: Python :: 3.10
Classifier: Programming Language :: Python :: 3.11
Requires-Python: <4,>=3.8
License-File: LICENSE
Requires-Dist: wagtail (>=4.1)
